{"includedArchiveIdentifiers":["OptimalRemote"],"interfaceLanguages":{"swift":[{"children":[{"title":"Classes","type":"groupMarker"},{"path":"\/documentation\/optimalremote\/oriasdkwindow","title":"ORIASdkWindow","type":"class"},{"children":[{"title":"Instance Properties","type":"groupMarker"},{"path":"\/documentation\/optimalremote\/oriasession\/remoteinputenabled","title":"var remoteInputEnabled: Bool","type":"property"},{"path":"\/documentation\/optimalremote\/oriasession\/voicechatenabled","title":"var voiceChatEnabled: Bool","type":"property"},{"path":"\/documentation\/optimalremote\/oriasession\/voicechatoverridesspeakerwhennoheadphones","title":"var voiceChatOverridesSpeakerWhenNoHeadphones: Bool","type":"property"},{"title":"Instance Methods","type":"groupMarker"},{"path":"\/documentation\/optimalremote\/oriasession\/close()","title":"func close() -> Bool","type":"method"},{"path":"\/documentation\/optimalremote\/oriasession\/open()","title":"func open() -> Bool","type":"method"},{"path":"\/documentation\/optimalremote\/oriasession\/setlocale(_:)","title":"func setLocale(Locale)","type":"method"},{"title":"Type Methods","type":"groupMarker"},{"path":"\/documentation\/optimalremote\/oriasession\/sessionforprofile(_:signedby:)","title":"static func sessionForProfile(String, signedBy: String) -> ORIASession?","type":"method"}],"path":"\/documentation\/optimalremote\/oriasession","title":"ORIASession","type":"class"},{"children":[{"title":"Instance Properties","type":"groupMarker"},{"path":"\/documentation\/optimalremote\/oriasessioncontroller\/appdelegate","title":"var appDelegate: ORIASessionControllerAppDelegate?","type":"property"},{"path":"\/documentation\/optimalremote\/oriasessioncontroller\/canopen","title":"var canOpen: Bool","type":"property"},{"path":"\/documentation\/optimalremote\/oriasessioncontroller\/voicechatenabled","title":"var voiceChatEnabled: Bool","type":"property"}],"path":"\/documentation\/optimalremote\/oriasessioncontroller","title":"ORIASessionController","type":"class"},{"children":[{"title":"Instance Methods","type":"groupMarker"},{"path":"\/documentation\/optimalremote\/oriawindow\/setorientation()","title":"func setOrientation()","type":"method"},{"path":"\/documentation\/optimalremote\/oriawindow\/setorientation(_:)","title":"func setOrientation(UIInterfaceOrientation)","type":"method"},{"path":"\/documentation\/optimalremote\/oriawindow\/setorientation(_:withduration:)-swift.method","title":"func setOrientation(UIInterfaceOrientation, withDuration: TimeInterval)","type":"method"},{"title":"Type Methods","type":"groupMarker"},{"path":"\/documentation\/optimalremote\/oriawindow\/setorientation(_:withduration:)-swift.type.method","title":"static func setOrientation(UIInterfaceOrientation, withDuration: TimeInterval)","type":"method"}],"path":"\/documentation\/optimalremote\/oriawindow","title":"ORIAWindow","type":"class"},{"title":"Protocols","type":"groupMarker"},{"children":[{"title":"Instance Methods","type":"groupMarker"},{"path":"\/documentation\/optimalremote\/oriasessioncontrollerappdelegate\/controllerdidcomplete(_:remoteconnectionhasestablished:)","title":"func controllerDidComplete(ORIASessionController, remoteConnectionHasEstablished: Bool)","type":"method"},{"path":"\/documentation\/optimalremote\/oriasessioncontrollerappdelegate\/controllerdidopen(_:)","title":"func controllerDidOpen(ORIASessionController)","type":"method"}],"path":"\/documentation\/optimalremote\/oriasessioncontrollerappdelegate","title":"ORIASessionControllerAppDelegate","type":"protocol"},{"title":"Enumerations","type":"groupMarker"},{"children":[{"title":"Enumeration Cases","type":"groupMarker"},{"path":"\/documentation\/optimalremote\/locale\/en","title":"case en","type":"case"},{"path":"\/documentation\/optimalremote\/locale\/ja","title":"case ja","type":"case"},{"path":"\/documentation\/optimalremote\/locale\/system","title":"case system","type":"case"},{"title":"Initializers","type":"groupMarker"},{"path":"\/documentation\/optimalremote\/locale\/init(rawvalue:)","title":"init?(rawValue: Int)","type":"init"},{"title":"Default Implementations","type":"groupMarker"},{"children":[{"title":"Operators","type":"groupMarker"},{"path":"\/documentation\/optimalremote\/locale\/!=(_:_:)","title":"static func != (Self, Self) -> Bool","type":"op"}],"path":"\/documentation\/optimalremote\/locale\/equatable-implementations","title":"Equatable Implementations","type":"symbol"},{"children":[{"title":"Instance Properties","type":"groupMarker"},{"path":"\/documentation\/optimalremote\/locale\/hashvalue","title":"var hashValue: Int","type":"property"},{"title":"Instance Methods","type":"groupMarker"},{"path":"\/documentation\/optimalremote\/locale\/hash(into:)","title":"func hash(into: inout Hasher)","type":"method"}],"path":"\/documentation\/optimalremote\/locale\/rawrepresentable-implementations","title":"RawRepresentable Implementations","type":"symbol"}],"path":"\/documentation\/optimalremote\/locale","title":"Locale","type":"enum"}],"path":"\/documentation\/optimalremote","title":"OptimalRemote","type":"module"}]},"schemaVersion":{"major":0,"minor":1,"patch":2}}